pngtools/__init__.py
pngtools/__main__.py
pngtools/bmp.py
pngtools/cli.py
pngtools/lib.py
pngtools/ppm.py
pngtools-1.0.2.dist-info/licenses/LICENSE
pngtools-1.0.2.dist-info/METADATA
pngtools-1.0.2.dist-info/WHEEL
pngtools-1.0.2.dist-info/top_level.txt
pngtools-1.0.2.dist-info/RECORD
