Metadata-Version: 2.4
Name: pngtools
Version: 1.0.2
Summary: Tiny CLI to explore PNGs
Author-email: n4n5 <its.just.n4n5@gmail.com>
License: MIT License
Project-URL: Homepage, https://github.com/its-just-nans/pngtools
Project-URL: Bug Tracker, https://github.com/its-just-nans/pngtools/issues
Keywords: png,tools,cli
Classifier: License :: OSI Approved :: MIT License
Classifier: Programming Language :: Python
Classifier: Programming Language :: Python :: 3
Requires-Python: >=3.6
License-File: LICENSE
Requires-Dist: cmd2<2,>=1
Requires-Dist: pyreadline3
Dynamic: license-file
